mongotransactions/__init__.py
mongotransactions/database.py
mongotransactions-1.2.5.dist-info/LICENSE
mongotransactions-1.2.5.dist-info/METADATA
mongotransactions-1.2.5.dist-info/WHEEL
mongotransactions-1.2.5.dist-info/top_level.txt
mongotransactions-1.2.5.dist-info/RECORD
