Metadata-Version: 2.1
Name: mongotransactions
Version: 1.2.5
Home-page: https://github.com/vorticalbox/mongotransactions
Author: vorticalbox
Author-email: vorticalbox@protonmail.com
License: GPL-3.0
Classifier: Programming Language :: Python :: 3
License-File: LICENSE
Requires-Dist: pymongo (~=3.11.0)
Requires-Dist: dnspython (~=2.0.0)
